psimpl/__init__.py
psimpl/psimpl.py
psimpl/psimpl_lib.py
PSIMPL-0.0.2.dist-info/LICENSE
PSIMPL-0.0.2.dist-info/METADATA
PSIMPL-0.0.2.dist-info/WHEEL
PSIMPL-0.0.2.dist-info/entry_points.txt
PSIMPL-0.0.2.dist-info/top_level.txt
PSIMPL-0.0.2.dist-info/RECORD
