Metadata-Version: 2.1
Name: PSIMPL
Version: 0.0.2
Summary: Peptide-Spectrum match IMPutation Library
Home-page: https://github.com/johnhalloran321/psimpl
Author: John T. Halloran
Author-email: johnhalloran321@gmail.com
License: Apache 2.0
Platform: any
Classifier: Natural Language :: English
Classifier: Development Status :: 3 - Alpha
Classifier: Intended Audience :: Science/Research
Classifier: License :: OSI Approved :: Apache Software License
Classifier: Topic :: Scientific/Engineering :: Bio-Informatics
Classifier: Operating System :: MacOS
Classifier: Operating System :: Microsoft :: Windows
Classifier: Operating System :: Unix
Classifier: Programming Language :: Python :: 3 :: Only
License-File: LICENSE
